squarespace.py
squarespace-0.0.2.dist-info/DESCRIPTION.rst
squarespace-0.0.2.dist-info/LICENSE.txt
squarespace-0.0.2.dist-info/METADATA
squarespace-0.0.2.dist-info/RECORD
squarespace-0.0.2.dist-info/WHEEL
squarespace-0.0.2.dist-info/metadata.json
squarespace-0.0.2.dist-info/top_level.txt
