Metadata-Version: 2.0
Name: squarespace
Version: 0.0.2
Summary: Library to access the Squarespace Commerce API.
Home-page: https://github.com/skullydazed/squarespace-python
Author: skullY
Author-email: skullydazed@gmail.com
License: MIT
Platform: UNKNOWN
Classifier: Development Status :: 5 - Production/Stable
Classifier: Intended Audience :: Developers
Classifier: Intended Audience :: System Administrators
Classifier: Natural Language :: English
Classifier: License :: OSI Approved :: MIT License
Classifier: Topic :: System :: Systems Administration
Requires-Dist: requests
